silica/Component.py
silica/SilicaTemplateResponse.py
silica/__init__.py
silica/concerns/Paginator.py
silica/errors.py
silica/inline_template_loader.py
silica/management/__init__.py
silica/management/commands/__init__.py
silica/management/commands/silica.py
silica/management/commands/silica_commands/__init__.py
silica/management/commands/silica_commands/create.py
silica/management/commands/silica_commands/mv.py
silica/management/commands/silica_commands/rm.py
silica/mixins/ValidatesProperties.py
silica/silica/ShortName.py
silica/silica/__init__.py
silica/silica/tests/__init__.py
silica/silica/tests/subfolder/ComponentInSubfolder.py
silica/silica/tests/subfolder/__init__.py
silica/static/alpine3.min.js
silica/static/alpine3.morph.min.js
silica/static/morphdom.js
silica/static/silica.js
silica/templatetags/__init__.py
silica/templatetags/silica.py
silica/templatetags/silica_scripts.py
silica/tests/SilicaBrowserTestCase.py
silica/tests/SilicaTestCase.py
silica/tests/__init__.py
silica/tests/templates/cache_persist_test_view.html
silica/tests/templates/component_subfolder_test.html
silica/tests/templates/component_tag_test.html
silica/tests/test_cache_expiry.py
silica/tests/test_checkboxes.py
silica/tests/test_class_property_modification.py
silica/tests/test_component_tag.py
silica/tests/test_dictionary_models.py
silica/tests/test_dispatch_browser_events.py
silica/tests/test_error_modal.py
silica/tests/test_events.py
silica/tests/test_inline_template.py
silica/tests/test_js_calls.py
silica/tests/test_lazy_loading.py
silica/tests/test_lifecycle_hooks.py
silica/tests/test_magic_methods.py
silica/tests/test_methods.py
silica/tests/test_modifier_debounce.py
silica/tests/test_morphing.py
silica/tests/test_ops.py
silica/tests/test_pagination.py
silica/tests/test_properties.py
silica/tests/test_property_expression_assignment.py
silica/tests/test_query_params.py
silica/tests/test_redirect.py
silica/tests/test_request_concurrency.py
silica/tests/test_script_tags_hydrated.py
django_silica-0.1.69.dist-info/LICENSE
django_silica-0.1.69.dist-info/METADATA
django_silica-0.1.69.dist-info/WHEEL
django_silica-0.1.69.dist-info/RECORD
