Metadata-Version: 2.1
Name: django-silica
Version: 0.1.69
Summary: A reusable Django app for Silica functionalities.
License: MIT
Keywords: django,components,ui,python
Author: Dyvenia
Requires-Python: >=3.8,<4
Classifier: Development Status :: 3 - Alpha
Classifier: Framework :: Django
Classifier: Intended Audience :: Developers
Classifier: License :: OSI Approved :: MIT License
Classifier: Programming Language :: Python :: 3
Classifier: Programming Language :: Python :: 3.8
Classifier: Programming Language :: Python :: 3.9
Classifier: Programming Language :: Python :: 3.10
Classifier: Programming Language :: Python :: 3.11
Classifier: Programming Language :: Python :: 3.12
Classifier: Programming Language :: Python :: 3.13
Provides-Extra: browser-tests
Requires-Dist: Django (>=4.2)
Requires-Dist: beautifulsoup4 (>=4.12.2,<4.13.0)
Requires-Dist: shortuuid (>=1.0.11,<1.1.0)
